.coveragerc
.dockerignore
.gitignore
.pre-commit-config.yaml
CNAME
Dockerfile
LICENSE
MANIFEST.in
README.md
lints.txt
py.typed
pyproject.toml
requirements.txt
requirements_dev.txt
requirements_doc.txt
setup.cfg
setup.py
tox.ini
.github/workflows/docs.yml
.github/workflows/github-actions.yml
deker/__init__.py
deker/arrays.py
deker/client.py
deker/collection.py
deker/config.py
deker/ctx.py
deker/dimensions.py
deker/errors.py
deker/flock.py
deker/integrity.py
deker/locks.py
deker/log.py
deker/managers.py
deker/schemas.py
deker/subset.py
deker/uri.py
deker/validators.py
deker/warnings.py
deker.egg-info/PKG-INFO
deker.egg-info/SOURCES.txt
deker.egg-info/dependency_links.txt
deker.egg-info/requires.txt
deker.egg-info/top_level.txt
deker/ABC/__init__.py
deker/ABC/base_adapters.py
deker/ABC/base_array.py
deker/ABC/base_collection.py
deker/ABC/base_dimension.py
deker/ABC/base_factory.py
deker/ABC/base_integrity.py
deker/ABC/base_locks.py
deker/ABC/base_managers.py
deker/ABC/base_schemas.py
deker/ABC/base_subset.py
deker/tools/__init__.py
deker/tools/array.py
deker/tools/decorators.py
deker/tools/path.py
deker/tools/schema.py
deker/tools/time.py
deker/types/__init__.py
deker/types/private/__init__.py
deker/types/private/classes.py
deker/types/private/enums.py
deker/types/private/shell.py
deker/types/private/typings.py
deker/types/public/__init__.py
deker/types/public/classes.py
docs/Makefile
docs/conf.py
docs/index.rst
docs/make.bat
docs/deker/data_management.rst
docs/deker/fine_tuning.rst
docs/deker/first_steps.rst
docs/deker/installation.rst
docs/deker/shell.rst
docs/deker/why_deker.rst
docs/deker/api/arrays.rst
docs/deker/api/client.rst
docs/deker/api/collection.rst
docs/deker/api/dimensions.rst
docs/deker/api/errors.rst
docs/deker/api/hdf5_options.rst
docs/deker/api/managers.rst
docs/deker/api/modules.rst
docs/deker/api/schemas.rst
docs/deker/api/subsets.rst
docs/deker/api/tuples.rst
docs/deker/api/warnings.rst
docs/deker/api/deker_tools/data.rst
docs/deker/api/deker_tools/modules.rst
docs/deker/api/deker_tools/path.rst
docs/deker/api/deker_tools/slices.rst
docs/deker/api/deker_tools/time.rst
